pyLSHash/__init__.py
pyLSHash/dist_func.py
pyLSHash/distance.py
pyLSHash/fuzzy_hash.py
pyLSHash/img_hash.py
pyLSHash/img_hist.py
pyLSHash/img_ssim.py
pyLSHash/lshash.py
pyLSHash/min_hash.py
pyLSHash/simhash.py
pyLSHash/storage.py
pyLSHash-0.2.3.dist-info/LICENSE
pyLSHash-0.2.3.dist-info/METADATA
pyLSHash-0.2.3.dist-info/WHEEL
pyLSHash-0.2.3.dist-info/top_level.txt
pyLSHash-0.2.3.dist-info/RECORD
